beerpong/__init__.py
beerpong/py.typed
beerpong/cli/__init__.py
beerpong/cli/beerpong.py
beerpong/cli/cli.py
beerpong/gui/__init__.py
beerpong/gui/gui.py
tests/__init__.py
tests/test_cli.py
beerpong-0.0.0.dist-info/LICENSE
beerpong-0.0.0.dist-info/METADATA
beerpong-0.0.0.dist-info/WHEEL
beerpong-0.0.0.dist-info/entry_points.txt
beerpong-0.0.0.dist-info/top_level.txt
beerpong-0.0.0.dist-info/RECORD
