Metadata-Version: 2.1
Name: beerpong
Version: 0.0.0
Summary: Bracketing tool with beerpong in mind
Home-page: https://github.com/juhannc/beerpong.git
Author: Johann Christensen
Author-email: johannchristensen@outlook.de
License: MIT
Project-URL: Source, https://github.com/juhannc/beerpong.git
Project-URL: Tracker, https://github.com/juhannc/beerpong/issues
Classifier: Development Status :: 4 - Beta
Classifier: Environment :: X11 Applications :: Qt
Classifier: Intended Audience :: End Users/Desktop
Classifier: License :: OSI Approved :: MIT License
Classifier: Natural Language :: English
Classifier: Operating System :: MacOS
Classifier: Operating System :: Microsoft :: Windows
Classifier: Operating System :: POSIX :: Linux
Classifier: Programming Language :: Python :: 3.8
Classifier: Topic :: Games/Entertainment
Requires-Python: >=3.8
License-File: LICENSE
Requires-Dist: PyQt6 ==6.5.2
Provides-Extra: all
Requires-Dist: coverage ; extra == 'all'
Requires-Dist: flake8 ; extra == 'all'
Requires-Dist: mypy ; extra == 'all'
Requires-Dist: pre-commit ; extra == 'all'
Requires-Dist: pycodestyle ; extra == 'all'
Requires-Dist: pytest >=6.2.2 ; extra == 'all'
Requires-Dist: pytest-cov ; extra == 'all'
Requires-Dist: pylint ; extra == 'all'
Provides-Extra: tests
Requires-Dist: coverage ; extra == 'tests'
Requires-Dist: flake8 ; extra == 'tests'
Requires-Dist: mypy ; extra == 'tests'
Requires-Dist: pre-commit ; extra == 'tests'
Requires-Dist: pycodestyle ; extra == 'tests'
Requires-Dist: pytest >=6.2.2 ; extra == 'tests'
Requires-Dist: pytest-cov ; extra == 'tests'
Requires-Dist: pylint ; extra == 'tests'
